langchain_kinetica/__init__.py
langchain_kinetica/llm_chat.py
langchain_kinetica/sa_datafile.py
langchain_kinetica/sa_dto.py
langchain_kinetica/sql_output.py
langchain_kinetica-1.0.0.dist-info/LICENSE
langchain_kinetica-1.0.0.dist-info/METADATA
langchain_kinetica-1.0.0.dist-info/WHEEL
langchain_kinetica-1.0.0.dist-info/top_level.txt
langchain_kinetica-1.0.0.dist-info/RECORD
