Metadata-Version: 2.1
Name: langchain-kinetica
Version: 1.0.0
Summary: Kinetica intefrace for Langchain.
Author-email: Chad Juliano <cjuliano@kinetica.com>
License: MIT License
Project-URL: Homepage, https://kinetica.com
Project-URL: Documentation, https://docs.kinetica.com/7.1/sql-gpt/
Project-URL: Repository, https://github.com/kineticadb/langchain-kinetica
Classifier: Programming Language :: Python :: 3
Requires-Python: >=3.10
License-File: LICENSE
Requires-Dist: gpudb >=7.1.9.10
Requires-Dist: langchain-core
Requires-Dist: pandas
